llm_structure.py
llm_structure-0.1.0.dist-info/LICENSE
llm_structure-0.1.0.dist-info/METADATA
llm_structure-0.1.0.dist-info/WHEEL
llm_structure-0.1.0.dist-info/entry_points.txt
llm_structure-0.1.0.dist-info/top_level.txt
llm_structure-0.1.0.dist-info/RECORD
