Metadata-Version: 2.2
Name: llm-structure
Version: 0.1.0
Summary: An llm plugin to add structured JSON output support to LLMs
Author: Kevin Madura
License: Apache-2.0
Project-URL: Homepage, https://github.com/kmad/llm-structure
Project-URL: Issues, https://github.com/kmad/llm-structure/issues
Classifier: License :: OSI Approved :: Apache Software License
Classifier: Topic :: Software Development :: Libraries :: Python Modules
Requires-Python: >=3.10
License-File: LICENSE
Requires-Dist: llm>=0.16
Requires-Dist: click>=8.0.0
Requires-Dist: pydantic>=2.0.0
